[
    {
        "time": "2025-03-31 19:30:50",
        "mean": 62.6,
        "max": 62.6,
        "min": 62.6
    },
    {
        "time": "2025-03-31 19:30:51",
        "mean": 67.55,
        "max": 69.2,
        "min": 65.5
    },
    {
        "time": "2025-03-31 19:30:52",
        "mean": 65.3,
        "max": 65.3,
        "min": 65.3
    },
    {
        "time": "2025-03-31 19:30:53",
        "mean": 66.53,
        "max": 67.2,
        "min": 65.8
    },
    {
        "time": "2025-03-31 19:30:54",
        "mean": 71.14,
        "max": 72.3,
        "min": 69.8
    },
    {
        "time": "2025-03-31 19:30:55",
        "mean": 71.5,
        "max": 71.5,
        "min": 71.5
    },
    {
        "time": "2025-03-31 19:30:56",
        "mean": 74.8,
        "max": 75.7,
        "min": 73.8
    },
    {
        "time": "2025-03-31 19:30:57",
        "mean": 72.5,
        "max": 72.5,
        "min": 72.5
    },
    {
        "time": "2025-03-31 19:30:58",
        "mean": 75.98,
        "max": 77.9,
        "min": 73.5
    },
    {
        "time": "2025-03-31 19:30:59",
        "mean": 78.3,
        "max": 78.3,
        "min": 78.3
    }
]